{
  "type": "FeatureCollection",
  "features": [
    {
      "type": "Feature",
      "geometry": {
        "type": "Point",
        "coordinates": [
          -52.676315,
          47.581375
        ]
      },
      "properties": {
        "Name": "Quidi Vidi Brewing Co.",
        "City": "St. John’s",
        "Province": "NL",
        "URL": "http://www.quidividibrewery.ca/",
        "Facebook": "https://www.facebook.com/quidi.brewery",
        "Twitter": "https://www.facebook.com/quidi.brewery",
        "Type": "Brewery",
        "marker-color": "#f00"
      }
    },
    {
      "type": "Feature",
      "geometry": {
        "type": "Point",
        "coordinates": [
          -52.807652,
          47.520607
        ]
      },
      "properties": {
        "Name": "Storm Brewing",
        "City": "Mt. Pearl",
        "Province": "NL",
        "URL": "http://www.stormbrewing.ca/",
        "Note": "No address available",
        "Type": "Brewery",
        "marker-color": "#f00"
      }
    },
    {
      "type": "Feature",
      "geometry": {
        "type": "Point",
        "coordinates": [
          -52.709717,
          47.562141
        ]
      },
      "properties": {
        "Name": "Yellowbelly Brewery & Pub",
        "City": "St. John's",
        "Province": "NL",
        "URL": "http://www.yellowbellybrewery.com/",
        "Facebook": "https://www.facebook.com/groups/35532264570/",
        "Twitter": "https://twitter.com/Yellowbellybrew",
        "Type": "Brewpub",
        "marker-color": "#00f"
      }
    }
  ]
}